.gitignore
.travis.yml
HISTORY.rst
MANIFEST.in
OVERVIEW.rst
README.rst
base.cfg
bootstrap.py
buildout.cfg
development.cfg
setup.py
sphinx.cfg
sphinx_requirements.txt
travis.cfg
docs/INSTALL.txt
docs/LICENSE.GPL
docs/LICENSE.txt
docs/conf.py
docs/corepackages.rst
docs/flexitopic.rst
docs/howto.rst
docs/index.rst
docs/installation.rst
docs/otherpackages.rst
docs/usersmap.rst
docs/images/1.png
docs/images/10.png
docs/images/11.png
docs/images/12.png
docs/images/13.png
docs/images/14.png
docs/images/2.png
docs/images/3.png
docs/images/4.png
docs/images/5.png
docs/images/6.png
docs/images/7.png
docs/images/8.png
docs/images/9.png
src/collective/__init__.py
src/collective.geo.bundle.egg-info/PKG-INFO
src/collective.geo.bundle.egg-info/SOURCES.txt
src/collective.geo.bundle.egg-info/dependency_links.txt
src/collective.geo.bundle.egg-info/entry_points.txt
src/collective.geo.bundle.egg-info/namespace_packages.txt
src/collective.geo.bundle.egg-info/not-zip-safe
src/collective.geo.bundle.egg-info/requires.txt
src/collective.geo.bundle.egg-info/top_level.txt
src/collective/geo/__init__.py
src/collective/geo/bundle/__init__.py
src/collective/geo/bundle/configure.zcml
src/collective/geo/bundle/profile.py
src/collective/geo/bundle/testing.py
src/collective/geo/bundle/testing.zcml
src/collective/geo/bundle/upgrades.py
src/collective/geo/bundle/upgrades.zcml
src/collective/geo/bundle/profiles/default/metadata.xml
src/collective/geo/bundle/profiles/testing/metadata.xml
src/collective/geo/bundle/profiles/testing/types.xml
src/collective/geo/bundle/profiles/testing/types/dexterity_content_with_geo_behaviour.xml
src/collective/geo/bundle/tests/__init__.py
src/collective/geo/bundle/tests/test_robot.py
src/collective/geo/bundle/tests/robotests/control_panel.robot
src/collective/geo/bundle/tests/robotests/dexterity.robot
src/collective/geo/bundle/tests/robotests/geo_reference_page.robot
src/collective/geo/bundle/tests/robotests/keywords.robot