Metadata-Version: 1.1
Name: collective.geo.bundle
Version: 2.3
Summary: Plone Maps (collective.geo)
Home-page: http://plone.org/products/collective.geo
Author: Giorgio Borelli
Author-email: giorgio@giorgioborelli.it
License: GPL
Keywords: Zope Plone GIS KML Google Maps Bing Yahoo OpenLayers
Platform: UNKNOWN
Classifier: Framework :: Plone
Classifier: Topic :: Internet
Classifier: Topic :: Scientific/Engineering :: GIS
Classifier: Programming Language :: Python
